remtmp/LICENSE
remtmp/README.MD
remtmp/__init__.py
remtmp/requirements.txt
remtmp/thirdparty.json
remtmp-0.10.dist-info/LICENSE.rst
remtmp-0.10.dist-info/METADATA
remtmp-0.10.dist-info/WHEEL
remtmp-0.10.dist-info/top_level.txt
remtmp-0.10.dist-info/RECORD
